vimbuffer/__init__.py
vimbuffer/py.typed
vimbuffer-0.1.4.dist-info/LICENSE
vimbuffer-0.1.4.dist-info/METADATA
vimbuffer-0.1.4.dist-info/WHEEL
vimbuffer-0.1.4.dist-info/top_level.txt
vimbuffer-0.1.4.dist-info/RECORD
