Metadata-Version: 2.1
Name: vimbuffer
Version: 0.1.4
Summary: Edit files, and strings in temporary vim (or some other console editor) buffers.
Home-page: https://github.com/seanbreckenridge/vimbuffer
Author: Sean Breckenridge
Author-email: seanbrecke@gmail.com
License: MIT
Keywords: vim editor stream
Platform: UNKNOWN
Classifier: License :: OSI Approved :: MIT License
Classifier: Programming Language :: Python
Classifier: Programming Language :: Python :: 3
Classifier: Programming Language :: Python :: 3.6
Classifier: Programming Language :: Python :: 3.7
Classifier: Programming Language :: Python :: 3.8
